d2j/__init__.py
d2j/converter.py
D2J-0.2.0.dist-info/LICENSE
D2J-0.2.0.dist-info/METADATA
D2J-0.2.0.dist-info/WHEEL
D2J-0.2.0.dist-info/top_level.txt
D2J-0.2.0.dist-info/RECORD
