Metadata-Version: 2.1
Name: D2J
Version: 0.2.0
Summary: A module for converting dates between Gregorian and Jalali calendars.
Home-page: https://github.com/eric-py/D2J
Author: Eric
Project-URL: GitHub, https://github.com/eric-py/D2J
Project-URL: Bug Tracker, https://github.com/eric-py/D2J/issues
Keywords: jalali,shamsi,gregorian,date,conversion,calendar
Classifier: Programming Language :: Python :: 3.6
Classifier: Programming Language :: Python :: 3.7
Classifier: Programming Language :: Python :: 3.8
Classifier: Programming Language :: Python :: 3.9
Classifier: Programming Language :: Python :: 3.10
Classifier: Programming Language :: Python :: 3.11
Classifier: Programming Language :: Python :: 3.12
Classifier: License :: OSI Approved :: MIT License
Classifier: Operating System :: OS Independent
Requires-Python: >=3.6
License-File: LICENSE
